Metadata-Version: 1.0
Name: uniout
Version: 0.3.3
Summary: Never see escaped bytes in output.
Home-page: https://github.com/moskytw/uniout
Author: Mosky
Author-email: mosky.tw@gmail.com
License: MIT
Platform: any
Classifier: Development Status :: 5 - Production/Stable
Classifier: Environment :: Console
Classifier: Intended Audience :: Developers
Classifier: License :: OSI Approved :: MIT License
Classifier: Operating System :: OS Independent
Classifier: Programming Language :: Python
Classifier: Topic :: Utilities
Classifier: Topic :: Software Development :: Libraries :: Python Modules
